applogs/__init__.py
applogs/admin.py
applogs/db_router.py
applogs/forms.py
applogs/handlers.py
applogs/models.py
applogs/tests.py
applogs/urls.py
applogs/utils.py
applogs/views.py
applogs/migrations/0001_initial.py
applogs/migrations/0002_auto_20170209_1817.py
applogs/migrations/0003_auto_20170530_2129.py
applogs/migrations/0004_auto_20170606_2139.py
applogs/migrations/0005_level_and_params_indexes.py
applogs/migrations/0006_auto_20180815_1747.py
applogs/migrations/0007_serverrecord_source.py
applogs/migrations/0008_auto_20180816_1223.py
applogs/migrations/0009_auto_20180816_1310.py
applogs/migrations/0010_auto_20181109_0836.py
applogs/migrations/0011_source_field.py
applogs/migrations/0012_warning_loglevel.py
applogs/migrations/0013_auto_20190123_1149.py
applogs/migrations/0014_auto_20190916_0730.py
applogs/migrations/__init__.py
applogs/templates/admin/applogs/clientrecord/change_list.html
applogs/templates/admin/applogs/serverrecord/change_list.html
saml/__init__.py
saml/backends.py
saml/methods.py
saml/pipelines.py
saml/urls.py
saml/views.py
saml/templates/admin/login_form.html
wfm_admin/__init__.py
wfm_admin/admin.py
wfm_admin/utils.py
wfm_admin/management/__init__.py
wfm_admin/management/commands/__init__.py
wfm_admin/management/commands/generate_groups.py
wfm_admin/static/wfm_admin/override.css
wfm_admin/templates/admin/base_site.html
wfm_admin/templates/admin/change_form.html
wfm_admin/templates/admin/change_list.html
wfm_admin/templates/admin/date_range_filter.html
wfm_admin/templates/admin/wfm_admin/app_index.html
wfm_admin/templates/admin/wfm_admin/index.html
xlsexport/__init__.py
xlsexport/admin.py
xlsexport/forms.py
xlsexport/methods.py
xlsexport/mixins.py
xlsexport/models.py
xlsexport/parsers.py
xlsexport/urls.py
xlsexport/migrations/0001_initial.py
xlsexport/migrations/0002_exporttemplate_default.py
xlsexport/migrations/0003_importtemplate.py
xlsexport/migrations/0004_alter_field_names.py
xlsexport/migrations/__init__.py
verme_logs-1.26.dist-info/LICENSE
verme_logs-1.26.dist-info/METADATA
verme_logs-1.26.dist-info/WHEEL
verme_logs-1.26.dist-info/top_level.txt
verme_logs-1.26.dist-info/RECORD
