Metadata-Version: 2.1
Name: verme-logs
Version: 1.26
Summary: Verme logs module to catch server processes and client browser errors
Home-page: https://www.verme.ru/
Author: Ilya Tabakov
Author-email: i.tabakov@verme.ru
License: BSD License
Platform: UNKNOWN
Classifier: Environment :: Web Environment
Classifier: Framework :: Django
Classifier: Framework :: Django :: 2.0
Classifier: Intended Audience :: Developers
Classifier: License :: OSI Approved :: BSD License
Classifier: Operating System :: OS Independent
Classifier: Programming Language :: Python
Classifier: Programming Language :: Python :: 3.5
Classifier: Programming Language :: Python :: 3.6
Classifier: Topic :: Internet :: WWW/HTTP
Classifier: Topic :: Internet :: WWW/HTTP :: Dynamic Content
Requires-Dist: Django (>=2.0)
Requires-Dist: social-auth-app-django
Requires-Dist: social-auth-core[saml]
Requires-Dist: xlrd
Requires-Dist: XlsxWriter
Requires-Dist: xlwt
